pyg4ometry/CMakeLists.txt
pyg4ometry/__init__.py
pyg4ometry/cli.py
pyg4ometry/config.py
pyg4ometry/exceptions.py
pyg4ometry/meshutils.py
pyg4ometry/transformation.py
pyg4ometry/utils.py
pyg4ometry/analysis/Data.py
pyg4ometry/analysis/Plot.py
pyg4ometry/analysis/__init__.py
pyg4ometry/analysis/bdsimData.py
pyg4ometry/analysis/flukaData.py
pyg4ometry/bdsim/__init__.py
pyg4ometry/bdsim/beam.py
pyg4ometry/bdsim/beamline.py
pyg4ometry/bdsim/element.py
pyg4ometry/bdsim/gmad.py
pyg4ometry/bdsim/options.py
pyg4ometry/bdsim/sampler.py
pyg4ometry/bdsim/scoring.py
pyg4ometry/compare/_Compare.py
pyg4ometry/compare/__init__.py
pyg4ometry/convert/__init__.py
pyg4ometry/convert/fluka2Geant4.py
pyg4ometry/convert/fluka2g4materials.py
pyg4ometry/convert/freecad2Fluka.py
pyg4ometry/convert/gdml2stl.py
pyg4ometry/convert/geant42Fluka.py
pyg4ometry/convert/geant42Geant4.py
pyg4ometry/convert/geant42Vtk.py
pyg4ometry/convert/oce2Geant4.py
pyg4ometry/convert/periodic-table.csv
pyg4ometry/convert/stl2gdml.py
pyg4ometry/convert/vis2oce.py
pyg4ometry/features/__init__.py
pyg4ometry/features/_accelerator.py
pyg4ometry/features/algos.py
pyg4ometry/fluka/Writer.py
pyg4ometry/fluka/__init__.py
pyg4ometry/fluka/body.py
pyg4ometry/fluka/boolean_algebra.py
pyg4ometry/fluka/card.py
pyg4ometry/fluka/directive.py
pyg4ometry/fluka/elcfield.py
pyg4ometry/fluka/extruder.py
pyg4ometry/fluka/flair.py
pyg4ometry/fluka/flair_template.flair
pyg4ometry/fluka/fluka_compounds.txt
pyg4ometry/fluka/fluka_elements.txt
pyg4ometry/fluka/fluka_lowenergyneut.txt
pyg4ometry/fluka/fluka_registry.py
pyg4ometry/fluka/lattice.py
pyg4ometry/fluka/material.py
pyg4ometry/fluka/mgnfield.py
pyg4ometry/fluka/preprocessor.py
pyg4ometry/fluka/reader.py
pyg4ometry/fluka/region.py
pyg4ometry/fluka/vector.py
pyg4ometry/fluka/vis.py
pyg4ometry/fluka/RegionExpression/README
pyg4ometry/fluka/RegionExpression/RegionLexer.g4
pyg4ometry/fluka/RegionExpression/RegionLexer.py
pyg4ometry-1.4.2.dist-info/METADATA
pyg4ometry-1.4.2.dist-info/WHEEL
pyg4ometry-1.4.2.dist-info/entry_points.txt
pyg4ometry-1.4.2.dist-info/RECORD
pyg4ometry-1.4.2.dist-info/licenses/LICENSE
