Metadata-Version: 2.1
Name: pyg4ometry
Version: 1.4.2
Summary: Geometry package for high energy physics (Geant4, Fluka)
Author-Email: "Stewart T. Boogert" <stewart.boogert@rhul.ac.uk>
Maintainer-Email: "Stewart T. Boogert" <stewart.boogert@rhul.ac.uk>
License:                     GNU GENERAL PUBLIC LICENSE
Classifier: Development Status :: 4 - Beta
Classifier: Intended Audience :: Developers
Classifier: Intended Audience :: Science/Research
Classifier: Operating System :: MacOS
Classifier: Operating System :: POSIX
Classifier: Operating System :: Unix
Classifier: Programming Language :: Python
Classifier: Programming Language :: Python :: 3
Classifier: Programming Language :: Python :: 3 :: Only
Classifier: Topic :: Scientific/Engineering
Classifier: Topic :: Scientific/Engineering :: Physics
Classifier: Topic :: Software Development
Project-URL: Homepage, https://github.com/g4edge/pyg4ometry
Project-URL: Documentation, https://pyg4ometry.readthedocs.io/
Project-URL: Bug Tracker, https://github.com/g4edge/pyg4ometry/issues
Requires-Python: >=3.6.8
Requires-Dist: importlib-resources
Requires-Dist: antlr4-python3-runtime==4.13.1
Requires-Dist: configparser
Requires-Dist: matplotlib
Requires-Dist: networkx>=3
Requires-Dist: numpy
Requires-Dist: pandas
Requires-Dist: scipy
Requires-Dist: sympy>=1.7
Requires-Dist: testtools
Requires-Dist: vtk
Provides-Extra: all
Requires-Dist: pyg4ometry[docs,test,usd]; extra == "all"
Provides-Extra: docs
Requires-Dist: furo; extra == "docs"
Requires-Dist: sphinx; extra == "docs"
Requires-Dist: sphinx-autoapi; extra == "docs"
Requires-Dist: sphinx-copybutton; extra == "docs"
Requires-Dist: sphinx-inline-tabs; extra == "docs"
Provides-Extra: test
Requires-Dist: g4edge-testdata; extra == "test"
Requires-Dist: pre-commit; extra == "test"
Requires-Dist: pytest>=6.0; extra == "test"
Requires-Dist: pytest-cov; extra == "test"
Provides-Extra: usd
Requires-Dist: usd-core; extra == "usd"
License-File: LICENSE
